{"cameraMode":{"drawMode":0,"name":"Shaded","section":"Shading Mode"},"sceneLighting":false,"audioPlay":false,"sceneViewState":{"m_AlwaysRefresh":false,"showFog":true,"showSkybox":false,"showFlares":true,"showImageEffects":true,"showParticleSystems":true,"showVisualEffectGraphs":true,"m_FxEnabled":true},"in2DMode":false,"pivot":{"x":48.80231857299805,"y":-0.33454906940460207,"z":8.401717185974121},"rotation":{"x":0.12896069884300233,"y":0.000598691520281136,"z":-0.00022437702864408493,"w":0.9917438626289368},"size":8.250725746154786,"orthographic":false}